cift/__init__.py
cift/_parser.py
cift/astextra.py
cift/debug.py
cift/err.py
cift/grammar.py
cift/parser.py
cift/semir.py
cift/shorthand.py
cift/types.py
cift-0.1.2.dist-info/licenses/LICENSE.md
cift-0.1.2.dist-info/METADATA
cift-0.1.2.dist-info/WHEEL
cift-0.1.2.dist-info/top_level.txt
cift-0.1.2.dist-info/RECORD
