Metadata-Version: 2.4
Name: cift
Version: 0.1.2
Summary: Caltech Intermediate Form parser in pure Python
Author-email: maybetree <maybetree48@proton.me>
License-Expression: AGPL-3.0-only
Classifier: Programming Language :: Python :: 3
Requires-Python: >=3
License-File: LICENSE.md
Requires-Dist: typing-extensions
Dynamic: license-file
